{"nodes": [{"id": "tst-onboarding-funnel-dashboard", "label": "TST: Onboarding Funnel Dashboard", "file_type": "document", "source_file": "docs/tst-onboarding-funnel-dashboard.md", "source_location": null, "source_url": null, "captured_at": null, "author": null, "contributor": null}, {"id": "concept-onboarding-funnel-steps", "label": "7-step PostHog onboarding funnel", "file_type": "document", "source_file": "docs/tst-onboarding-funnel-dashboard.md", "source_location": null, "source_url": null, "captured_at": null, "author": null, "contributor": null}], "edges": [{"source": "tst-onboarding-funnel-dashboard", "target": "concept-onboarding-funnel-steps", "relation": "references", "confidence": "EXTRACTED", "confidence_score": 1.0, "source_file": "docs/tst-onboarding-funnel-dashboard.md", "source_location": null, "weight": 1.0}, {"source": "tst-onboarding-funnel-dashboard", "target": "concept-posthog-analytics", "relation": "shares_data_with", "confidence": "EXTRACTED", "confidence_score": 1.0, "source_file": "docs/tst-onboarding-funnel-dashboard.md", "source_location": null, "weight": 1.0}, {"source": "concept-onboarding-funnel-steps", "target": "concept-wizard-skipped-event", "relation": "conceptually_related_to", "confidence": "INFERRED", "confidence_score": 0.7, "source_file": "docs/tst-onboarding-funnel-dashboard.md", "source_location": null, "weight": 0.7}], "hyperedges": []}