{"nodes": [{"id": "prd_visual_strategy_validation", "label": "PRD: Visual Strategy Validation Feedback", "file_type": "document", "source_file": "docs/prd-visual-strategy-validation-feedback.md", "source_location": null, "source_url": null, "captured_at": null, "author": null, "contributor": null}, {"id": "concept_canvas_block_highlight", "label": "Canvas block error/warning highlight", "file_type": "document", "source_file": "docs/prd-visual-strategy-validation-feedback.md", "source_location": null, "source_url": null, "captured_at": null, "author": null, "contributor": null}, {"id": "rationale_reduce_error_hunting", "label": "WHY: Reduce time hunting errors in side panel", "file_type": "document", "source_file": "docs/prd-visual-strategy-validation-feedback.md", "source_location": null, "source_url": null, "captured_at": null, "author": null, "contributor": null}], "edges": [{"source": "prd_visual_strategy_validation", "target": "concept_canvas_block_highlight", "relation": "references", "confidence": "EXTRACTED", "confidence_score": 1.0, "source_file": "docs/prd-visual-strategy-validation-feedback.md", "source_location": null, "weight": 1.0}, {"source": "rationale_reduce_error_hunting", "target": "prd_visual_strategy_validation", "relation": "rationale_for", "confidence": "EXTRACTED", "confidence_score": 1.0, "source_file": "docs/prd-visual-strategy-validation-feedback.md", "source_location": null, "weight": 1.0}], "hyperedges": []}