{"nodes": [{"id": "prd-volatility-metrics", "label": "PRD: Volatility Metrics in Market Overview", "file_type": "document", "source_file": "docs/prd-volatility-metrics-market-overview.md", "source_location": null, "source_url": null, "captured_at": null, "author": null, "contributor": null}, {"id": "concept-volatility-metrics", "label": "Volatility Metrics (ATR, stddev)", "file_type": "document", "source_file": "docs/prd-volatility-metrics-market-overview.md", "source_location": null, "source_url": null, "captured_at": null, "author": null, "contributor": null}, {"id": "concept-market-overview", "label": "Market Overview Dashboard", "file_type": "document", "source_file": "docs/prd-volatility-metrics-market-overview.md", "source_location": null, "source_url": null, "captured_at": null, "author": null, "contributor": null}], "edges": [{"source": "prd-volatility-metrics", "target": "concept-volatility-metrics", "relation": "references", "confidence": "EXTRACTED", "confidence_score": 0.95, "source_file": "docs/prd-volatility-metrics-market-overview.md", "source_location": null, "weight": 1.0}, {"source": "prd-volatility-metrics", "target": "concept-market-overview", "relation": "references", "confidence": "EXTRACTED", "confidence_score": 0.95, "source_file": "docs/prd-volatility-metrics-market-overview.md", "source_location": null, "weight": 1.0}, {"source": "prd-volatility-metrics", "target": "tst-market-sentiment-indicators", "relation": "conceptually_related_to", "confidence": "INFERRED", "confidence_score": 0.75, "source_file": "docs/prd-volatility-metrics-market-overview.md", "source_location": null, "weight": 0.75}], "hyperedges": []}